regex_string_generator/__init__.py
regex_string_generator/py.typed
regex_string_generator-0.1.0.dist-info/LICENSE
regex_string_generator-0.1.0.dist-info/METADATA
regex_string_generator-0.1.0.dist-info/WHEEL
regex_string_generator-0.1.0.dist-info/top_level.txt
regex_string_generator-0.1.0.dist-info/RECORD
