Metadata-Version: 2.1
Name: regex-string-generator
Version: 0.1.0
Summary: Generates random strings that match a given regex pattern
Home-page: https://github.com/tsv1/regex-string-generator
Author: Nikita Tsvetkov
Author-email: tsv1@fastmail.com
License: Apache-2.0
Classifier: License :: OSI Approved :: Apache Software License
Classifier: Programming Language :: Python :: 3.8
Classifier: Programming Language :: Python :: 3.9
Classifier: Programming Language :: Python :: 3.10
Classifier: Programming Language :: Python :: 3.11
Classifier: Programming Language :: Python :: 3.12
Classifier: Typing :: Typed
Requires-Python: >=3.8
License-File: LICENSE
Requires-Dist: blahblah<2.0,>=1.8
